pyservx/__init__.py
pyservx/file_operations.py
pyservx/html_generator.py
pyservx/request_handler.py
pyservx/server.py
pyservx-3.0.1.dist-info/licenses/LICENSE
pyservx-3.0.1.dist-info/METADATA
pyservx-3.0.1.dist-info/WHEEL
pyservx-3.0.1.dist-info/entry_points.txt
pyservx-3.0.1.dist-info/top_level.txt
pyservx-3.0.1.dist-info/RECORD
