Metadata-Version: 2.4
Name: pyservx
Version: 3.0.1
Summary: A feature-rich Python HTTP server for file sharing with fixed layout UI, real-time search, direct media downloads, permanent text clipboard, dark/light themes, and QR code access.
Author-email: Subz3r0x01 <subz3r0x01@protonmail.com>
License: MIT
Project-URL: Homepage, https://github.com/SubZ3r0-0x01/pyservx
Project-URL: Repository, https://github.com/SubZ3r0-0x01/pyservx
Keywords: file server,http server,file sharing,fixed layout,real-time search,media downloads,text clipboard,qrcode,pyservx,dark mode,light mode,notepad,text editor,file preview,analytics,thumbnails
Classifier: Development Status :: 4 - Beta
Classifier: Intended Audience :: Developers
Classifier: Intended Audience :: End Users/Desktop
Classifier: Programming Language :: Python :: 3
Classifier: Programming Language :: Python :: 3.6
Classifier: Programming Language :: Python :: 3.7
Classifier: Programming Language :: Python :: 3.8
Classifier: Programming Language :: Python :: 3.9
Classifier: Programming Language :: Python :: 3.10
Classifier: Programming Language :: Python :: 3.11
Classifier: Programming Language :: Python :: 3.12
Classifier: Operating System :: OS Independent
Classifier: Topic :: Internet :: WWW/HTTP :: HTTP Servers
Classifier: Topic :: System :: Filesystems
Requires-Python: >=3.6
License-File: LICENSE
Requires-Dist: qrcode
Requires-Dist: Pillow
Dynamic: license-file
